src/__init__.py
src/board.py
learner_board-1.0.1.dist-info/LICENSE
learner_board-1.0.1.dist-info/METADATA
learner_board-1.0.1.dist-info/WHEEL
learner_board-1.0.1.dist-info/entry_points.txt
learner_board-1.0.1.dist-info/top_level.txt
learner_board-1.0.1.dist-info/RECORD
