Metadata-Version: 2.1
Name: learner-board
Version: 1.0.1
Home-page: https://github.com/cyan-io/learner-board
Download-URL: https://github.com/cyan-io/learner-board/releases
Author: Cyan@https://github.com/cyan-io
Author-email: cyan-io@outlook.com
License: MPL 2.0
Platform: any
Requires-Python: >=3.6
License-File: LICENSE
Requires-Dist: requests
Requires-Dist: prettytable
